dbc_to_dbf-1.0.1.dist-info/licenses/LICENSE
dbctodbf/__init__.py
dbctodbf/__main__.py
dbctodbf/blast_decompress.py
dbctodbf/dbc_decompress.py
dbc_to_dbf-1.0.1.dist-info/METADATA
dbc_to_dbf-1.0.1.dist-info/WHEEL
dbc_to_dbf-1.0.1.dist-info/entry_points.txt
dbc_to_dbf-1.0.1.dist-info/top_level.txt
dbc_to_dbf-1.0.1.dist-info/RECORD
