Metadata-Version: 2.4
Name: dbc-to-dbf
Version: 1.0.1
Summary: Convert DBC files (compressed DBF - DATASUS) into DBF using the PKWare BLAST decompression algorithm
Author-email: Mozar Silva <mozar.silva@gmail.com>
License: zlib License
Project-URL: Homepage, https://github.com/mozaru/dbc-to-dbf
Project-URL: Repository, https://github.com/mozaru/dbc-to-dbf
Keywords: dbc,DATASUS,dbf,pkware,blast,decompression,converter
Classifier: Programming Language :: Python :: 3
Classifier: Operating System :: OS Independent
Classifier: License :: OSI Approved :: zlib/libpng License
Classifier: Topic :: Software Development :: Libraries :: Python Modules
Classifier: Topic :: Utilities
Classifier: Intended Audience :: Developers
Requires-Python: >=3.7
License-File: LICENSE
Dynamic: license-file
